jambazid/demo/__init__.py
jambazid/demo/data/schema.json
jambazid/demo/module.py
jambazid/demo/py.typed
jambazid/demo/subpackage/__init__.py
jambazid/demo/subpackage/submodule.py
jambazid_cache-0.0.0.dist-info/METADATA
jambazid_cache-0.0.0.dist-info/WHEEL
jambazid_cache-0.0.0.dist-info/entry_points.txt
jambazid_cache-0.0.0.dist-info/RECORD
